axterminator/__init__.py
axterminator/axterminator.abi3.so
axterminator/cli.py
axterminator/pytest_plugin.py
axterminator/recorder.py
axterminator/sync.py
axterminator/vlm.py
axterminator-0.3.2.dist-info/METADATA
axterminator-0.3.2.dist-info/WHEEL
axterminator-0.3.2.dist-info/entry_points.txt
axterminator-0.3.2.dist-info/licenses/LICENSE-APACHE
axterminator-0.3.2.dist-info/licenses/LICENSE-MIT
axterminator-0.3.2.dist-info/RECORD
