Metadata-Version: 2.4
Name: axterminator
Version: 0.3.2
Classifier: Development Status :: 3 - Alpha
Classifier: Environment :: MacOS X
Classifier: Intended Audience :: Developers
Classifier: License :: OSI Approved :: MIT License
Classifier: License :: OSI Approved :: Apache Software License
Classifier: Operating System :: MacOS :: MacOS X
Classifier: Programming Language :: Python :: 3
Classifier: Programming Language :: Python :: 3.9
Classifier: Programming Language :: Python :: 3.10
Classifier: Programming Language :: Python :: 3.11
Classifier: Programming Language :: Python :: 3.12
Classifier: Programming Language :: Python :: 3.13
Classifier: Programming Language :: Rust
Classifier: Topic :: Software Development :: Testing
Classifier: Topic :: Software Development :: Quality Assurance
Requires-Dist: pytest>=7.0 ; extra == 'dev'
Requires-Dist: pytest-asyncio>=0.21 ; extra == 'dev'
Requires-Dist: pytest-cov>=4.0 ; extra == 'dev'
Requires-Dist: mypy>=1.0 ; extra == 'dev'
Requires-Dist: ruff>=0.1.0 ; extra == 'dev'
Requires-Dist: mlx-vlm>=0.1.0 ; extra == 'vlm'
Requires-Dist: mlx-vlm>=0.1.0 ; extra == 'vlm-all'
Requires-Dist: anthropic>=0.25.0 ; extra == 'vlm-all'
Requires-Dist: openai>=1.0.0 ; extra == 'vlm-all'
Requires-Dist: google-generativeai>=0.3.0 ; extra == 'vlm-all'
Requires-Dist: httpx>=0.25.0 ; extra == 'vlm-all'
Requires-Dist: anthropic>=0.25.0 ; extra == 'vlm-anthropic'
Requires-Dist: google-generativeai>=0.3.0 ; extra == 'vlm-gemini'
Requires-Dist: httpx>=0.25.0 ; extra == 'vlm-ollama'
Requires-Dist: openai>=1.0.0 ; extra == 'vlm-openai'
Provides-Extra: dev
Provides-Extra: vlm
Provides-Extra: vlm-all
Provides-Extra: vlm-anthropic
Provides-Extra: vlm-gemini
Provides-Extra: vlm-ollama
Provides-Extra: vlm-openai
License-File: LICENSE-APACHE
License-File: LICENSE-MIT
Summary: World's most superior macOS GUI testing framework with background testing
Keywords: macos,gui,testing,accessibility,automation,background
Author-email: Mikko <mikko@broa.biz>
License: MIT OR Apache-2.0
Requires-Python: >=3.9
Project-URL: Documentation, https://github.com/MikkoParkkola/axterminator#readme
Project-URL: Homepage, https://github.com/MikkoParkkola/axterminator
Project-URL: Issues, https://github.com/MikkoParkkola/axterminator/issues
Project-URL: Repository, https://github.com/MikkoParkkola/axterminator
